ctec_consumer
