Metadata-Version: 1.0
Name: ctec-consumer
Version: 0.4.7
Summary: 189 rabbitMQ consumer
Home-page: http://www.189.cn
Author: ZhangZhaoyuan
Author-email: zhangzhy@chinatelecom.cn
License: UNKNOWN
Platform: UNKNOWN
